MAYA/__init__.py
MAYA/VIA/__init__.py
MAYA/VIA/uform.py
MAYA/VIA/uuid.py
MAYA/VIA/vsmf.py
MAYA/utils/__init__.py
MAYA/utils/crypto.py
MAYA/utils/date.py
vialib3-1.0.0.dist-info/LICENSE
vialib3-1.0.0.dist-info/METADATA
vialib3-1.0.0.dist-info/WHEEL
vialib3-1.0.0.dist-info/top_level.txt
vialib3-1.0.0.dist-info/RECORD
